daaja/__init__.py
daaja/augmentors/__init__.py
daaja/augmentors/sentence/__init__.py
daaja/augmentors/sentence/back_translation_augmentor.py
daaja/augmentors/sentence/contextual_augmentor.py
daaja/augmentors/sentence/randam_delete_augmentor.py
daaja/augmentors/sentence/randam_insert_augmentor.py
daaja/augmentors/sentence/randam_swap_augmentor.py
daaja/augmentors/sentence/sentence_augmentor.py
daaja/augmentors/sentence/synonym_replace_augmentor.py
daaja/augmentors/sequence_labeling/__init__.py
daaja/augmentors/sequence_labeling/labelwise_token_replacement_augmentor.py
daaja/augmentors/sequence_labeling/mention_replacement_augmentor.py
daaja/augmentors/sequence_labeling/sequence_labeling_augmentor.py
daaja/augmentors/sequence_labeling/shuffle_within_segments_augmentor.py
daaja/augmentors/sequence_labeling/synonym_replacement_augmentor.py
daaja/augmentors/sequence_labeling/utils.py
daaja/flows/__init__.py
daaja/flows/sequential_flow.py
daaja/flows/sequential_sequence_labeling_flow.py
daaja/methods/eda/__init__.py
daaja/methods/eda/easy_data_augmentor.py
daaja/methods/eda/run.py
daaja/methods/ner_sda/__init__.py
daaja/methods/ner_sda/run.py
daaja/methods/ner_sda/simple_data_augmentation_for_ner.py
daaja/resouces.py
daaja/tokenizer.py
daaja-0.0.8.dist-info/WHEEL
daaja-0.0.8.dist-info/METADATA
daaja-0.0.8.dist-info/RECORD
