Metadata-Version: 2.1
Name: daaja
Version: 0.0.8
Summary: NLP data augmentation tool
License: MIT
Author: Koga Kobayashi
Author-email: kajyuuen@gmail.com
Requires-Python: >=3.7.1,<4.0
Classifier: License :: OSI Approved :: MIT License
Classifier: Programming Language :: Python :: 3
Classifier: Programming Language :: Python :: 3.10
Classifier: Programming Language :: Python :: 3.8
Classifier: Programming Language :: Python :: 3.9
Requires-Dist: SudachiDict-core (>=20211220,<20211221)
Requires-Dist: SudachiPy (>=0.6.3,<0.7.0)
Requires-Dist: fugashi (>=1.1.2,<2.0.0)
Requires-Dist: ipadic (>=1.0.0,<2.0.0)
Requires-Dist: numpy (>=1.3)
Requires-Dist: pandas (>=1.2)
Requires-Dist: requests (>=2.27.1,<3.0.0)
Requires-Dist: sentencepiece (>=0.1.96,<0.2.0)
Requires-Dist: torch (>=1.10.2,<2.0.0)
Requires-Dist: tqdm (>=4.62.3,<5.0.0)
Requires-Dist: transformers (>=4.16.2,<5.0.0)
